ptijson/__init__.py
ptijson/__main__.py
ptijson-0.1.0.dist-info/entry_points.txt
ptijson-0.1.0.dist-info/WHEEL
ptijson-0.1.0.dist-info/METADATA
ptijson-0.1.0.dist-info/RECORD
